news_python/__init__.py
news_python/country.py
news_python/global_news.py
news_python/news_api.py
news_python-1.0.0.dist-info/LICENSE
news_python-1.0.0.dist-info/METADATA
news_python-1.0.0.dist-info/WHEEL
news_python-1.0.0.dist-info/top_level.txt
news_python-1.0.0.dist-info/RECORD
