Metadata-Version: 2.1
Name: news-python
Version: 1.0.0
Summary: A Python API Wrapper for the https://newsapi.org/ JSON API
Home-page: https://github.com/MakufonSkifto/news-python
Author: MakufonSkifto
License: GNU General Public License v3.0
Platform: UNKNOWN
Classifier: Programming Language :: Python :: 3
Classifier: License :: OSI Approved :: MIT License
Requires-Python: >=3.6
Requires-Dist: requests
